{
  "schemaVersion": 1,
  "id": "informaticaproject",
  "version": "${version}",

  "name": "Broodje kaas",
  "description": "Broodje kaas maken.",
  "authors": [
    "Rio",
    "Wassim",
    "Pavle"
  ],
  "contact": {
    "homepage": "https://bit.ly/3qWX6wO",
    "sources": ""
  },

  "license": "CC0-1.0",
  "icon": "assets/InformaticaProject/icon.png",

  "environment": "*",
  "entrypoints": {
    "main": [
      "project.mod.broodjekaas.BroodjeKaas"
    ]
  },
  "mixins": [
    "informaticaproject.mixins.json"
  ],

  "depends": {
    "fabricloader": ">=0.7.4",
    "fabric": "*",
    "minecraft": "1.16.x"
  },
  "suggests": {
    "another-mod": "*"
  }
}
